Opencv3AnzhuoYingyongBianchengChuyiFix1/README.md
Opencv3AnzhuoYingyongBianchengChuyiFix1/__init__.py
Opencv3AnzhuoYingyongBianchengChuyiFix1/__main__.py
Opencv3AnzhuoYingyongBianchengChuyiFix1/file.epub
Opencv3AnzhuoYingyongBianchengChuyiFix1/index.html
Opencv3AnzhuoYingyongBianchengChuyiFix1/css/__init__.py
Opencv3AnzhuoYingyongBianchengChuyiFix1/css/annotations.css
Opencv3AnzhuoYingyongBianchengChuyiFix1/css/main.css
Opencv3AnzhuoYingyongBianchengChuyiFix1/css/normalize.css
Opencv3AnzhuoYingyongBianchengChuyiFix1/css/popup.css
Opencv3AnzhuoYingyongBianchengChuyiFix1/font/__init__.py
Opencv3AnzhuoYingyongBianchengChuyiFix1/font/fontello.eot
Opencv3AnzhuoYingyongBianchengChuyiFix1/font/fontello.svg
Opencv3AnzhuoYingyongBianchengChuyiFix1/font/fontello.ttf
Opencv3AnzhuoYingyongBianchengChuyiFix1/font/fontello.woff
Opencv3AnzhuoYingyongBianchengChuyiFix1/img/__init__.py
Opencv3AnzhuoYingyongBianchengChuyiFix1/img/annotator-glyph-sprite.png
Opencv3AnzhuoYingyongBianchengChuyiFix1/img/annotator-icon-sprite.png
Opencv3AnzhuoYingyongBianchengChuyiFix1/img/apple-touch-icon.png
Opencv3AnzhuoYingyongBianchengChuyiFix1/img/cancelfullscreen.png
Opencv3AnzhuoYingyongBianchengChuyiFix1/img/close.png
Opencv3AnzhuoYingyongBianchengChuyiFix1/img/fullscreen.png
Opencv3AnzhuoYingyongBianchengChuyiFix1/img/loader.gif
Opencv3AnzhuoYingyongBianchengChuyiFix1/img/menu-icon.png
Opencv3AnzhuoYingyongBianchengChuyiFix1/img/save.png
Opencv3AnzhuoYingyongBianchengChuyiFix1/img/saved.png
Opencv3AnzhuoYingyongBianchengChuyiFix1/img/settings-s.png
Opencv3AnzhuoYingyongBianchengChuyiFix1/img/settings.png
Opencv3AnzhuoYingyongBianchengChuyiFix1/img/star.png
Opencv3AnzhuoYingyongBianchengChuyiFix1/js/__init__.py
Opencv3AnzhuoYingyongBianchengChuyiFix1/js/epub.js
Opencv3AnzhuoYingyongBianchengChuyiFix1/js/epub.min.js
Opencv3AnzhuoYingyongBianchengChuyiFix1/js/epub.min.map
Opencv3AnzhuoYingyongBianchengChuyiFix1/js/hooks.min.js
Opencv3AnzhuoYingyongBianchengChuyiFix1/js/hooks.min.map
opencv3_anzhuo_yingyong_biancheng_chuyi_fix1-2025.3.25.1.dist-info/METADATA
opencv3_anzhuo_yingyong_biancheng_chuyi_fix1-2025.3.25.1.dist-info/WHEEL
opencv3_anzhuo_yingyong_biancheng_chuyi_fix1-2025.3.25.1.dist-info/entry_points.txt
opencv3_anzhuo_yingyong_biancheng_chuyi_fix1-2025.3.25.1.dist-info/top_level.txt
opencv3_anzhuo_yingyong_biancheng_chuyi_fix1-2025.3.25.1.dist-info/RECORD
